LICENSE
README.rst
setup.py
ecosystem_notebooks.egg-info/PKG-INFO
ecosystem_notebooks.egg-info/SOURCES.txt
ecosystem_notebooks.egg-info/dependency_links.txt
ecosystem_notebooks.egg-info/requires.txt
ecosystem_notebooks.egg-info/top_level.txt
prediction/__init__.py
prediction/export_to_notebook.py
prediction/jwt_access.py
prediction/nlp_utils.py
prediction/notebook_functions.py
prediction/prediction_utils.py
prediction/request_utils.py
prediction/apis/__init__.py
prediction/apis/algorithm_client_pulse.py
prediction/apis/auth_controller.py
prediction/apis/data_ingestion_engine.py
prediction/apis/data_management_engine.py
prediction/apis/data_munging_engine.py
prediction/apis/deployment_management.py
prediction/apis/deployment_management_super.py
prediction/apis/ecosystem_generation_engine.py
prediction/apis/ecosystem_home.py
prediction/apis/ecosystem_main.py
prediction/apis/ecosystem_user_profiles.py
prediction/apis/functions.py
prediction/apis/interactions.py
prediction/apis/online_learning_management.py
prediction/apis/prediction_engine.py
prediction/apis/quickflat.py
prediction/apis/settings_controller.py
prediction/apis/transaction_categorization.py
prediction/apis/user_controller.py
prediction/apis/utilities.py
prediction/apis/worker_aws.py
prediction/apis/worker_file_service.py
prediction/apis/worker_google.py
prediction/apis/worker_h2o.py
prediction/apis/worker_microsoft.py
prediction/apis/worker_open_ai.py
prediction/apis/worker_uber.py
prediction/endpoints/__init__.py
prediction/endpoints/algorithm_client_pulse.py
prediction/endpoints/auth_controller.py
prediction/endpoints/data_ingestion_engine.py
prediction/endpoints/data_management_engine.py
prediction/endpoints/data_munging_engine.py
prediction/endpoints/ecosystem_generation_engine.py
prediction/endpoints/ecosystem_home.py
prediction/endpoints/ecosystem_main.py
prediction/endpoints/ecosystem_user_profiles.py
prediction/endpoints/interaction.py
prediction/endpoints/prediction_engine.py
prediction/endpoints/settings_controller.py
prediction/endpoints/transaction_categorization.py
prediction/endpoints/user_controller.py
prediction/endpoints/utilities.py
prediction/endpoints/worker_aws.py
