Metadata-Version: 2.4
Name: ecosystem-notebooks
Version: 0.1.50
Summary: Ecosystem Notebooks is a wrapper for the Ecosystem API servers.
Home-page: https://github.com/ecosystemai/ecosystem-notebooks
Author: EcosystemAi
Author-email: jay@ecosystem.ai
License: MIT
Classifier: Development Status :: 5 - Production/Stable
Classifier: Intended Audience :: Science/Research
Classifier: Intended Audience :: Developers
Classifier: License :: OSI Approved :: MIT License
Classifier: Operating System :: POSIX :: Linux
Classifier: Programming Language :: Python :: 3
Classifier: Programming Language :: Python :: 3.12
Classifier: Framework :: Jupyter :: JupyterLab
License-File: LICENSE
Requires-Dist: requests
Requires-Dist: pymongo
Dynamic: author
Dynamic: author-email
Dynamic: classifier
Dynamic: description
Dynamic: home-page
Dynamic: license
Dynamic: license-file
Dynamic: requires-dist
Dynamic: summary
